{"Flume": [{"date": "2016-05-27", "genres": ["Electro"], "label": "Transgressive"}, {"date": "2013-11-11", "genres": ["Electro"], "label": "Transgressive"}, {"date": "2013-11-11", "genres": ["Electro"], "label": "Transgressive"}, {"date": "2012-11-12", "genres": ["Electro"], "label": "Transgressive"}, {"date": "2013-11-22", "genres": ["Electro", "Dance"], "label": "Future Classic"}, {"date": "2016-04-21", "genres": ["Electro"], "label": "Transgressive"}, {"date": "2016-03-04", "genres": ["Electro"], "label": "Transgressive"}, {"date": "2016-03-25", "genres": ["Electro"], "label": "Future Classic"}, {"date": "2016-03-25", "genres": ["Electro"], "label": "Transgressive"}, {"date": "2016-01-05", "genres": ["Electro", "Dance"], "label": "Future Classic"}, {"date": "2002-01-01", "genres": ["Pop", "Rock"], "label": "Bittersweet Records"}]}